sort_order_field/__init__.py
sort_order_field/admin_widgets.py
sort_order_field/fields.py
sort_order_field/tests.py
sort_order_field/migrations/__init__.py
sort_order_field/static/sort_order_field/sort_order_field.css
sort_order_field/static/sort_order_field/sort_order_field.js
django_sort_order_field-1.2.dist-info/LICENSE
django_sort_order_field-1.2.dist-info/METADATA
django_sort_order_field-1.2.dist-info/WHEEL
django_sort_order_field-1.2.dist-info/top_level.txt
django_sort_order_field-1.2.dist-info/RECORD
