Metadata-Version: 2.1
Name: django-sort-order-field
Version: 1.2
Summary: A Django model field for controlling sort order.
Home-page: https://github.com/dylanmccall/django-sort-order-field
Author: Dylan McCall
Author-email: dylan@dylanmccall.ca
License: BSD License
Keywords: django sort field
Platform: UNKNOWN
Classifier: Environment :: Web Environment
Classifier: Framework :: Django
Classifier: Framework :: Django :: 1.11
Classifier: Intended Audience :: Developers
Classifier: License :: OSI Approved :: BSD License
Classifier: Operating System :: OS Independent
Classifier: Programming Language :: Python
Classifier: Programming Language :: Python :: 3.5
Classifier: Programming Language :: Python :: 3.6
Classifier: Topic :: Internet :: WWW/HTTP
Classifier: Topic :: Internet :: WWW/HTTP :: Dynamic Content
